{"id": "Hq_05YpTOcY", "title": "Alaska y Dinarama - Ni t\u00fa ni nadie", "formats": [{"asr": 48000, "filesize": 1357823, "format_id": "249", "format_note": "tiny", "fps": null, "height": null, "quality": 0, "tbr": 49.979, "url": "https://rr6---sn-0opoxu-ihv6.googlevideo.com/videoplayback?expire=1670726114&ei=gu2UY_9XjpKTBv6nibAB&ip=189.173.225.87&id=o-AHpzqefD4gQpHlbjS8sloFS3JnLMJZ_M7Ez71zHRC6-4&itag=249&source=youtube&requiressl=yes&mh=im&mm=31%2C29&mn=sn-0opoxu-ihv6%2Csn-q4flrnss&ms=au%2Crdu&mv=m&mvi=6&pl=24&initcwndbps=777500&vprv=1&mime=audio%2Fwebm&ns=6LIPfmBZtH9oNZtAUL1FTK8J&gir=yes&clen=1357823&dur=217.341&lmt=1613008524054607&mt=1670704150&fvip=1&keepalive=yes&fexp=24001373%2C24007246&beids=24432615&c=WEB&txp=5431432&n=sj2V4ZivplNHcOzkn&sparams=expire%2Cei%2Cip%2Cid%2Citag%2Csource%2Crequiressl%2Cvprv%2Cmime%2Cns%2Cgir%2Cclen%2Cdur%2Clmt&lsparams=mh%2Cmm%2Cmn%2Cms%2Cmv%2Cmvi%2Cpl%2Cinitcwndbps&lsig=AG3C_xAwRQIgXefevgWxkDPza6QsGMYzb1ObLh3RHYIu1Qyur6ku4QECIQDHEils0jATJ9EgxeMtphQipe2wi9Fj75S-tek06hxurQ%3D%3D&sig=AOq0QJ8wRQIhAPaJSqmJZkaF_hbTcCm2euIIk8OqrVbVwxMcDpoQ4olaAiAYKM8W_ZFFPisT0bfLLSlrmzyzYx6A_M8O_2CC3wV2WA==", "width": null, "ext": "webm", "vcodec": "none", "acodec": "opus", "abr": 49.979, "downloader_options": {"http_chunk_size": 10485760}, "container": "webm_dash", "format": "249 - audio only (tiny)", "protocol": "https", "http_headers": {"User-Agent": "Mozilla/5.0 (Windows NT 10.0; Win64; x64) AppleWebKit/537.36 (KHTML, like Gecko) Chrome/74.0.3729.53 Safari/537.36", "Accept-Charset": "ISO-8859-1,utf-8;q=0.7,*;q=0.7", "Accept": "text/html,application/xhtml+xml,application/xml;q=0.9,*/*;q=0.8", "Accept-Encoding": "gzip, deflate", "Accept-Language": "en-us,en;q=0.5"}}, {"asr": 48000, "filesize": 1794727, "format_id": "250", "format_note": "tiny", "fps": null, "height": null, "quality": 0, "tbr": 66.061, "url": "https://rr6---sn-0opoxu-ihv6.googlevideo.com/videoplayback?expire=1670726114&ei=gu2UY_9XjpKTBv6nibAB&ip=189.173.225.87&id=o-AHpzqefD4gQpHlbjS8sloFS3JnLMJZ_M7Ez71zHRC6-4&itag=250&source=youtube&requiressl=yes&mh=im&mm=31%2C29&mn=sn-0opoxu-ihv6%2Csn-q4flrnss&ms=au%2Crdu&mv=m&mvi=6&pl=24&initcwndbps=777500&vprv=1&mime=audio%2Fwebm&ns=6LIPfmBZtH9oNZtAUL1FTK8J&gir=yes&clen=1794727&dur=217.341&lmt=1613008523467832&mt=1670704150&fvip=1&keepalive=yes&fexp=24001373%2C24007246&beids=24432615&c=WEB&txp=5431432&n=sj2V4ZivplNHcOzkn&sparams=expire%2Cei%2Cip%2Cid%2Citag%2Csource%2Crequiressl%2Cvprv%2Cmime%2Cns%2Cgir%2Cclen%2Cdur%2Clmt&lsparams=mh%2Cmm%2Cmn%2Cms%2Cmv%2Cmvi%2Cpl%2Cinitcwndbps&lsig=AG3C_xAwRAIgeNPOCTpVrKclKqgSk0cN7KV4SUAf7mc7qjB8iJgFMkcCIAhtQocXHm1fXtVcIYtCw37jb9JG_Qmpa51ykLd-FBjO&sig=AOq0QJ8wRgIhAI_iGRlLM1JA_8O_ucjN1V2OJT3wxpKnH9_J0Mq425YKAiEA8yJlpDKMb7zJrF4BSDsFovPCG_tlYWPswfcfKCqi5jc=", "width": null, "ext": "webm", "vcodec": "none", "acodec": "opus", "abr": 66.061, "downloader_options": {"http_chunk_size": 10485760}, "container": "webm_dash", "format": "250 - audio only (tiny)", "protocol": "https", "http_headers": {"User-Agent": "Mozilla/5.0 (Windows NT 10.0; Win64; x64) AppleWebKit/537.36 (KHTML, like Gecko) Chrome/74.0.3729.53 Safari/537.36", "Accept-Charset": "ISO-8859-1,utf-8;q=0.7,*;q=0.7", "Accept": "text/html,application/xhtml+xml,application/xml;q=0.9,*/*;q=0.8", "Accept-Encoding": "gzip, deflate", "Accept-Language": "en-us,en;q=0.5"}}, {"asr": 44100, "filesize": 3518827, "format_id": "140", "format_note": "tiny", "fps": null, "height": null, "quality": 0, "tbr": 129.496, "url": "https://rr6---sn-0opoxu-ihv6.googlevideo.com/videoplayback?expire=1670726114&ei=gu2UY_9XjpKTBv6nibAB&ip=189.173.225.87&id=o-AHpzqefD4gQpHlbjS8sloFS3JnLMJZ_M7Ez71zHRC6-4&itag=140&source=youtube&requiressl=yes&mh=im&mm=31%2C29&mn=sn-0opoxu-ihv6%2Csn-q4flrnss&ms=au%2Crdu&mv=m&mvi=6&pl=24&initcwndbps=777500&vprv=1&mime=audio%2Fmp4&ns=6LIPfmBZtH9oNZtAUL1FTK8J&gir=yes&clen=3518827&dur=217.385&lmt=1613008524493773&mt=1670704150&fvip=1&keepalive=yes&fexp=24001373%2C24007246&beids=24432615&c=WEB&txp=5431432&n=sj2V4ZivplNHcOzkn&sparams=expire%2Cei%2Cip%2Cid%2Citag%2Csource%2Crequiressl%2Cvprv%2Cmime%2Cns%2Cgir%2Cclen%2Cdur%2Clmt&lsparams=mh%2Cmm%2Cmn%2Cms%2Cmv%2Cmvi%2Cpl%2Cinitcwndbps&lsig=AG3C_xAwRQIhAMgyf5WR7tDEdf5BAxGfMLW4y6nnrUVM6bhaUcppQ7P5AiAwu_Yp2LziOzllwYHyd7_DUk13sR975u5Wt3S9Yxj4jw%3D%3D&sig=AOq0QJ8wRgIhANPIkDy23zr7hv8w9drfQl6yqEXmuWCHZqVzIlUAf2sAAiEA0cCK94hYGIPct5q3QNKJVBJJ4EvldVIqowicF5GXbzA=", "width": null, "ext": "m4a", "vcodec": "none", "acodec": "mp4a.40.2", "abr": 129.496, "downloader_options": {"http_chunk_size": 10485760}, "container": "m4a_dash", "format": "140 - audio only (tiny)", "protocol": "https", "http_headers": {"User-Agent": "Mozilla/5.0 (Windows NT 10.0; Win64; x64) AppleWebKit/537.36 (KHTML, like Gecko) Chrome/74.0.3729.53 Safari/537.36", "Accept-Charset": "ISO-8859-1,utf-8;q=0.7,*;q=0.7", "Accept": "text/html,application/xhtml+xml,application/xml;q=0.9,*/*;q=0.8", "Accept-Encoding": "gzip, deflate", "Accept-Language": "en-us,en;q=0.5"}}, {"asr": 48000, "filesize": 3550764, "format_id": "251", "format_note": "tiny", "fps": null, "height": null, "quality": 0, "tbr": 130.698, "url": "https://rr6---sn-0opoxu-ihv6.googlevideo.com/videoplayback?expire=1670726114&ei=gu2UY_9XjpKTBv6nibAB&ip=189.173.225.87&id=o-AHpzqefD4gQpHlbjS8sloFS3JnLMJZ_M7Ez71zHRC6-4&itag=251&source=youtube&requiressl=yes&mh=im&mm=31%2C29&mn=sn-0opoxu-ihv6%2Csn-q4flrnss&ms=au%2Crdu&mv=m&mvi=6&pl=24&initcwndbps=777500&vprv=1&mime=audio%2Fwebm&ns=6LIPfmBZtH9oNZtAUL1FTK8J&gir=yes&clen=3550764&dur=217.341&lmt=1613008542066066&mt=1670704150&fvip=1&keepalive=yes&fexp=24001373%2C24007246&beids=24432615&c=WEB&txp=5431432&n=sj2V4ZivplNHcOzkn&sparams=expire%2Cei%2Cip%2Cid%2Citag%2Csource%2Crequiressl%2Cvprv%2Cmime%2Cns%2Cgir%2Cclen%2Cdur%2Clmt&lsparams=mh%2Cmm%2Cmn%2Cms%2Cmv%2Cmvi%2Cpl%2Cinitcwndbps&lsig=AG3C_xAwRgIhAJ2lT7wIudtrkrFOVktCQckK-ByhemqQFt1-dxHue76uAiEApDcESI6HMsw5ivH-BLa-clk7ec-fBHx0XskGjYNsWAM%3D&sig=AOq0QJ8wRQIhANGD-hk_ePjfU-at2MPfncaAvlQGglf20ZKdSANBr_dPAiBnWCUmvC3n3pEC0Zw_co6lpVG7JE_uqpwgIFW02hb_fQ==", "width": null, "ext": "webm", "vcodec": "none", "acodec": "opus", "abr": 130.698, "downloader_options": {"http_chunk_size": 10485760}, "container": "webm_dash", "format": "251 - audio only (tiny)", "protocol": "https", "http_headers": {"User-Agent": "Mozilla/5.0 (Windows NT 10.0; Win64; x64) AppleWebKit/537.36 (KHTML, like Gecko) Chrome/74.0.3729.53 Safari/537.36", "Accept-Charset": "ISO-8859-1,utf-8;q=0.7,*;q=0.7", "Accept": "text/html,application/xhtml+xml,application/xml;q=0.9,*/*;q=0.8", "Accept-Encoding": "gzip, deflate", "Accept-Language": "en-us,en;q=0.5"}}, {"asr": null, "filesize": 1752505, "format_id": "278", "format_note": "144p", "fps": 30, "height": 144, "quality": 0, "tbr": 64.514, "url": "https://rr6---sn-0opoxu-ihv6.googlevideo.com/videoplayback?expire=1670726114&ei=gu2UY_9XjpKTBv6nibAB&ip=189.173.225.87&id=o-AHpzqefD4gQpHlbjS8sloFS3JnLMJZ_M7Ez71zHRC6-4&itag=278&aitags=133%2C160%2C242%2C278%2C394%2C395&source=youtube&requiressl=yes&mh=im&mm=31%2C29&mn=sn-0opoxu-ihv6%2Csn-q4flrnss&ms=au%2Crdu&mv=m&mvi=6&pl=24&initcwndbps=777500&vprv=1&mime=video%2Fwebm&ns=6LIPfmBZtH9oNZtAUL1FTK8J&gir=yes&clen=1752505&dur=217.316&lmt=1613008876289194&mt=1670704150&fvip=1&keepalive=yes&fexp=24001373%2C24007246&beids=24432615&c=WEB&txp=5432432&n=sj2V4ZivplNHcOzkn&sparams=expire%2Cei%2Cip%2Cid%2Caitags%2Csource%2Crequiressl%2Cvprv%2Cmime%2Cns%2Cgir%2Cclen%2Cdur%2Clmt&lsparams=mh%2Cmm%2Cmn%2Cms%2Cmv%2Cmvi%2Cpl%2Cinitcwndbps&lsig=AG3C_xAwRQIgNd7m7zmGapMjWV4D2NPW-lS5BnzN5OKsKpKLTQtL8tgCIQCkhOfwsXrmanqJBC4jcgux6XMQygnRhBAtk-VsNFru9A%3D%3D&sig=AOq0QJ8wRAIgLHZ5cSXUuxUqyMJnYZBw4DuSuwEGWZxTVAL-H69UB1kCIDhHWW3SLglz1P6Fwf4d-1Tab-jnpA0ISGAx4iLqtl3o", "width": 194, "ext": "webm", "vcodec": "vp9", "acodec": "none", "vbr": 64.514, "downloader_options": {"http_chunk_size": 10485760}, "container": "webm_dash", "format": "278 - 194x144 (144p)", "protocol": "https", "http_headers": {"User-Agent": "Mozilla/5.0 (Windows NT 10.0; Win64; x64) AppleWebKit/537.36 (KHTML, like Gecko) Chrome/74.0.3729.53 Safari/537.36", "Accept-Charset": "ISO-8859-1,utf-8;q=0.7,*;q=0.7", "Accept": "text/html,application/xhtml+xml,application/xml;q=0.9,*/*;q=0.8", "Accept-Encoding": "gzip, deflate", "Accept-Language": "en-us,en;q=0.5"}}, {"asr": null, "filesize": 1986509, "format_id": "394", "format_note": "144p", "fps": 30, "height": 144, "quality": 0, "tbr": 73.128, "url": "https://rr6---sn-0opoxu-ihv6.googlevideo.com/videoplayback?expire=1670726114&ei=gu2UY_9XjpKTBv6nibAB&ip=189.173.225.87&id=o-AHpzqefD4gQpHlbjS8sloFS3JnLMJZ_M7Ez71zHRC6-4&itag=394&aitags=133%2C160%2C242%2C278%2C394%2C395&source=youtube&requiressl=yes&mh=im&mm=31%2C29&mn=sn-0opoxu-ihv6%2Csn-q4flrnss&ms=au%2Crdu&mv=m&mvi=6&pl=24&initcwndbps=777500&vprv=1&mime=video%2Fmp4&ns=6LIPfmBZtH9oNZtAUL1FTK8J&gir=yes&clen=1986509&dur=217.317&lmt=1630517197042552&mt=1670704150&fvip=1&keepalive=yes&fexp=24001373%2C24007246&beids=24432615&c=WEB&txp=1436434&n=sj2V4ZivplNHcOzkn&sparams=expire%2Cei%2Cip%2Cid%2Caitags%2Csource%2Crequiressl%2Cvprv%2Cmime%2Cns%2Cgir%2Cclen%2Cdur%2Clmt&lsparams=mh%2Cmm%2Cmn%2Cms%2Cmv%2Cmvi%2Cpl%2Cinitcwndbps&lsig=AG3C_xAwRQIhAPxQ_zChR0bpeV9DB8nTpGEJWB2kpJx_r5UTywSabYCGAiAmgpXeGGy5myvJ_Z3lbZfqG1AR-EzTPCZB-3TONyRcVA%3D%3D&sig=AOq0QJ8wRQIgFDoZkMm0P1cUXjlf2QJIxGGcJLTfR-ZGij3QIvvR4HQCIQD0lMbWhSXxnpcLc1lNJJlmBMcrrnjRyOQWo543AdJCTw==", "width": 194, "ext": "mp4", "vcodec": "av01.0.00M.08", "acodec": "none", "vbr": 73.128, "downloader_options": {"http_chunk_size": 10485760}, "container": "mp4_dash", "format": "394 - 194x144 (144p)", "protocol": "https", "http_headers": {"User-Agent": "Mozilla/5.0 (Windows NT 10.0; Win64; x64) AppleWebKit/537.36 (KHTML, like Gecko) Chrome/74.0.3729.53 Safari/537.36", "Accept-Charset": "ISO-8859-1,utf-8;q=0.7,*;q=0.7", "Accept": "text/html,application/xhtml+xml,application/xml;q=0.9,*/*;q=0.8", "Accept-Encoding": "gzip, deflate", "Accept-Language": "en-us,en;q=0.5"}}, {"asr": null, "filesize": 2057821, "format_id": "160", "format_note": "144p", "fps": 30, "height": 144, "quality": 0, "tbr": 75.753, "url": "https://rr6---sn-0opoxu-ihv6.googlevideo.com/videoplayback?expire=1670726114&ei=gu2UY_9XjpKTBv6nibAB&ip=189.173.225.87&id=o-AHpzqefD4gQpHlbjS8sloFS3JnLMJZ_M7Ez71zHRC6-4&itag=160&aitags=133%2C160%2C242%2C278%2C394%2C395&source=youtube&requiressl=yes&mh=im&mm=31%2C29&mn=sn-0opoxu-ihv6%2Csn-q4flrnss&ms=au%2Crdu&mv=m&mvi=6&pl=24&initcwndbps=777500&vprv=1&mime=video%2Fmp4&ns=6LIPfmBZtH9oNZtAUL1FTK8J&gir=yes&clen=2057821&dur=217.317&lmt=1613009050385993&mt=1670704150&fvip=1&keepalive=yes&fexp=24001373%2C24007246&beids=24432615&c=WEB&txp=5432432&n=sj2V4ZivplNHcOzkn&sparams=expire%2Cei%2Cip%2Cid%2Caitags%2Csource%2Crequiressl%2Cvprv%2Cmime%2Cns%2Cgir%2Cclen%2Cdur%2Clmt&lsparams=mh%2Cmm%2Cmn%2Cms%2Cmv%2Cmvi%2Cpl%2Cinitcwndbps&lsig=AG3C_xAwRQIgKZSESt6TvUy0dngLkXtITno8xtD9ytc8rgcsK6xphEYCIQCn-dnvr0EcG3254UJc2tuP5zCmaKF3PRVb66bD0C0jIQ%3D%3D&sig=AOq0QJ8wRQIgMhUKNkENIfQNLlXOyMa2tDmoWwHP8vEaOp0THBxJw08CIQCUnOtsIzJZ-hlrgu50zAmk0t5KapYMSsFjOGci9AI2ZA==", "width": 194, "ext": "mp4", "vcodec": "avc1.4d400c", "acodec": "none", "vbr": 75.753, "downloader_options": {"http_chunk_size": 10485760}, "container": "mp4_dash", "format": "160 - 194x144 (144p)", "protocol": "https", "http_headers": {"User-Agent": "Mozilla/5.0 (Windows NT 10.0; Win64; x64) AppleWebKit/537.36 (KHTML, like Gecko) Chrome/74.0.3729.53 Safari/537.36", "Accept-Charset": "ISO-8859-1,utf-8;q=0.7,*;q=0.7", "Accept": "text/html,application/xhtml+xml,application/xml;q=0.9,*/*;q=0.8", "Accept-Encoding": "gzip, deflate", "Accept-Language": "en-us,en;q=0.5"}}, {"asr": null, "filesize": 3729678, "format_id": "242", "format_note": "240p", "fps": 30, "height": 240, "quality": 1, "tbr": 137.299, "url": "https://rr6---sn-0opoxu-ihv6.googlevideo.com/videoplayback?expire=1670726114&ei=gu2UY_9XjpKTBv6nibAB&ip=189.173.225.87&id=o-AHpzqefD4gQpHlbjS8sloFS3JnLMJZ_M7Ez71zHRC6-4&itag=242&aitags=133%2C160%2C242%2C278%2C394%2C395&source=youtube&requiressl=yes&mh=im&mm=31%2C29&mn=sn-0opoxu-ihv6%2Csn-q4flrnss&ms=au%2Crdu&mv=m&mvi=6&pl=24&initcwndbps=777500&vprv=1&mime=video%2Fwebm&ns=6LIPfmBZtH9oNZtAUL1FTK8J&gir=yes&clen=3729678&dur=217.316&lmt=1613008876412415&mt=1670704150&fvip=1&keepalive=yes&fexp=24001373%2C24007246&beids=24432615&c=WEB&txp=5432432&n=sj2V4ZivplNHcOzkn&sparams=expire%2Cei%2Cip%2Cid%2Caitags%2Csource%2Crequiressl%2Cvprv%2Cmime%2Cns%2Cgir%2Cclen%2Cdur%2Clmt&lsparams=mh%2Cmm%2Cmn%2Cms%2Cmv%2Cmvi%2Cpl%2Cinitcwndbps&lsig=AG3C_xAwRgIhANK2gZ_no8gES6E68EvpiRumXHYDnIuU4oXpas2EEACAAiEA-oH6qXAKcpnp86Unmlug0LzFpEQT_viK6oNcRFqe2IM%3D&sig=AOq0QJ8wRQIhAMLvflUL36nxCvvymGh8Tp8ywRVmb9-5eTuRqOiTRbtPAiBVdkVfK1_EGSseHjkOgujrXgbzyUgyyJ66b6_gikjt5A==", "width": 322, "ext": "webm", "vcodec": "vp9", "acodec": "none", "vbr": 137.299, "downloader_options": {"http_chunk_size": 10485760}, "container": "webm_dash", "format": "242 - 322x240 (240p)", "protocol": "https", "http_headers": {"User-Agent": "Mozilla/5.0 (Windows NT 10.0; Win64; x64) AppleWebKit/537.36 (KHTML, like Gecko) Chrome/74.0.3729.53 Safari/537.36", "Accept-Charset": "ISO-8859-1,utf-8;q=0.7,*;q=0.7", "Accept": "text/html,application/xhtml+xml,application/xml;q=0.9,*/*;q=0.8", "Accept-Encoding": "gzip, deflate", "Accept-Language": "en-us,en;q=0.5"}}, {"asr": null, "filesize": 3984500, "format_id": "395", "format_note": "240p", "fps": 30, "height": 240, "quality": 1, "tbr": 146.679, "url": "https://rr6---sn-0opoxu-ihv6.googlevideo.com/videoplayback?expire=1670726114&ei=gu2UY_9XjpKTBv6nibAB&ip=189.173.225.87&id=o-AHpzqefD4gQpHlbjS8sloFS3JnLMJZ_M7Ez71zHRC6-4&itag=395&aitags=133%2C160%2C242%2C278%2C394%2C395&source=youtube&requiressl=yes&mh=im&mm=31%2C29&mn=sn-0opoxu-ihv6%2Csn-q4flrnss&ms=au%2Crdu&mv=m&mvi=6&pl=24&initcwndbps=777500&vprv=1&mime=video%2Fmp4&ns=6LIPfmBZtH9oNZtAUL1FTK8J&gir=yes&clen=3984500&dur=217.317&lmt=1630517203682004&mt=1670704150&fvip=1&keepalive=yes&fexp=24001373%2C24007246&beids=24432615&c=WEB&txp=1436434&n=sj2V4ZivplNHcOzkn&sparams=expire%2Cei%2Cip%2Cid%2Caitags%2Csource%2Crequiressl%2Cvprv%2Cmime%2Cns%2Cgir%2Cclen%2Cdur%2Clmt&lsparams=mh%2Cmm%2Cmn%2Cms%2Cmv%2Cmvi%2Cpl%2Cinitcwndbps&lsig=AG3C_xAwRgIhAMzfSNv7kdvR0WdBJfoU5YjTWwSPeQHnJ4lOXL_8Q1wjAiEA8yWroBOHrYvkDWeYIv8vYuQMIHzQ9NnZdSHaX-sPA0k%3D&sig=AOq0QJ8wRgIhALjBxqNkCm8oSlb_1MHRbh2TPwXs2_UgEcJp3izJvrv7AiEA9xP7UQ3fD9DkQoHWqKN8mOG1V4etp1ogXUN_Xb8oD4E=", "width": 322, "ext": "mp4", "vcodec": "av01.0.00M.08", "acodec": "none", "vbr": 146.679, "downloader_options": {"http_chunk_size": 10485760}, "container": "mp4_dash", "format": "395 - 322x240 (240p)", "protocol": "https", "http_headers": {"User-Agent": "Mozilla/5.0 (Windows NT 10.0; Win64; x64) AppleWebKit/537.36 (KHTML, like Gecko) Chrome/74.0.3729.53 Safari/537.36", "Accept-Charset": "ISO-8859-1,utf-8;q=0.7,*;q=0.7", "Accept": "text/html,application/xhtml+xml,application/xml;q=0.9,*/*;q=0.8", "Accept-Encoding": "gzip, deflate", "Accept-Language": "en-us,en;q=0.5"}}, {"asr": null, "filesize": 4369185, "format_id": "133", "format_note": "240p", "fps": 30, "height": 240, "quality": 1, "tbr": 160.84, "url": "https://rr6---sn-0opoxu-ihv6.googlevideo.com/videoplayback?expire=1670726114&ei=gu2UY_9XjpKTBv6nibAB&ip=189.173.225.87&id=o-AHpzqefD4gQpHlbjS8sloFS3JnLMJZ_M7Ez71zHRC6-4&itag=133&aitags=133%2C160%2C242%2C278%2C394%2C395&source=youtube&requiressl=yes&mh=im&mm=31%2C29&mn=sn-0opoxu-ihv6%2Csn-q4flrnss&ms=au%2Crdu&mv=m&mvi=6&pl=24&initcwndbps=777500&vprv=1&mime=video%2Fmp4&ns=6LIPfmBZtH9oNZtAUL1FTK8J&gir=yes&clen=4369185&dur=217.317&lmt=1613009050365747&mt=1670704150&fvip=1&keepalive=yes&fexp=24001373%2C24007246&beids=24432615&c=WEB&txp=5432432&n=sj2V4ZivplNHcOzkn&sparams=expire%2Cei%2Cip%2Cid%2Caitags%2Csource%2Crequiressl%2Cvprv%2Cmime%2Cns%2Cgir%2Cclen%2Cdur%2Clmt&lsparams=mh%2Cmm%2Cmn%2Cms%2Cmv%2Cmvi%2Cpl%2Cinitcwndbps&lsig=AG3C_xAwRQIhALkMqtuVW3qVctyoraQUQEgJjIgF1afEQNLGX9HsyKthAiA9cs62XnKTqn2p-bdm0BV48mxOKz76nTJq5-kV9B3I-w%3D%3D&sig=AOq0QJ8wRAIgZ-Mr8t3wOxJWC02nx3NX2ILW1e0dBaroU4-pmf8AV1kCICSoThNs60JcwvPzlcj9QGi0tr7rQd5KLOcMxG0IwuGD", "width": 322, "ext": "mp4", "vcodec": "avc1.4d400d", "acodec": "none", "vbr": 160.84, "downloader_options": {"http_chunk_size": 10485760}, "container": "mp4_dash", "format": "133 - 322x240 (240p)", "protocol": "https", "http_headers": {"User-Agent": "Mozilla/5.0 (Windows NT 10.0; Win64; x64) AppleWebKit/537.36 (KHTML, like Gecko) Chrome/74.0.3729.53 Safari/537.36", "Accept-Charset": "ISO-8859-1,utf-8;q=0.7,*;q=0.7", "Accept": "text/html,application/xhtml+xml,application/xml;q=0.9,*/*;q=0.8", "Accept-Encoding": "gzip, deflate", "Accept-Language": "en-us,en;q=0.5"}}, {"asr": 44100, "filesize": 14232711, "format_id": "18", "format_note": "240p", "fps": 30, "height": 262, "quality": 1, "tbr": 523.778, "url": "https://rr6---sn-0opoxu-ihv6.googlevideo.com/videoplayback?expire=1670726114&ei=gu2UY_9XjpKTBv6nibAB&ip=189.173.225.87&id=o-AHpzqefD4gQpHlbjS8sloFS3JnLMJZ_M7Ez71zHRC6-4&itag=18&source=youtube&requiressl=yes&mh=im&mm=31%2C29&mn=sn-0opoxu-ihv6%2Csn-q4flrnss&ms=au%2Crdu&mv=m&mvi=6&pl=24&initcwndbps=777500&vprv=1&mime=video%2Fmp4&ns=48vzQtgGt8D6OF_Ix63ZQf4J&gir=yes&clen=14232711&ratebypass=yes&dur=217.385&lmt=1613008567714271&mt=1670704150&fvip=1&fexp=24001373%2C24007246&beids=24432615&c=WEB&txp=5438432&n=hg90v1J9EoT5OOvh4&sparams=expire%2Cei%2Cip%2Cid%2Citag%2Csource%2Crequiressl%2Cvprv%2Cmime%2Cns%2Cgir%2Cclen%2Cratebypass%2Cdur%2Clmt&lsparams=mh%2Cmm%2Cmn%2Cms%2Cmv%2Cmvi%2Cpl%2Cinitcwndbps&lsig=AG3C_xAwRQIhAIToNF6ywFSU0Nolu5row5J9MGldpb04rDslEA7gIuw9AiBWi1JJdDDn9nrXd5KKtv6aNq5lZrwKePHgBsiqtog79w%3D%3D&sig=AOq0QJ8wRAIgBbgBoeGBmTiHvzWCbMTEF8FSUGMYqOt8aiBT35TfKbACIFJoa7FXutOnwvvIe6toTi5sOvWkSGlQJt2cr5Cx74eL", "width": 352, "ext": "mp4", "vcodec": "avc1.42001E", "acodec": "mp4a.40.2", "format": "18 - 352x262 (240p)", "protocol": "https", "http_headers": {"User-Agent": "Mozilla/5.0 (Windows NT 10.0; Win64; x64) AppleWebKit/537.36 (KHTML, like Gecko) Chrome/74.0.3729.53 Safari/537.36", "Accept-Charset": "ISO-8859-1,utf-8;q=0.7,*;q=0.7", "Accept": "text/html,application/xhtml+xml,application/xml;q=0.9,*/*;q=0.8", "Accept-Encoding": "gzip, deflate", "Accept-Language": "en-us,en;q=0.5"}}], "thumbnails": [{"height": 94, "url": "https://i.ytimg.com/vi/Hq_05YpTOcY/hqdefault.jpg?sqp=-oaymwEbCKgBEF5IVfKriqkDDggBFQAAiEIYAXABwAEG&rs=AOn4CLCkOqx28RI_J-ETxsSE6RI7huCiww", "width": 168, "resolution": "168x94", "id": "0"}, {"height": 110, "url": "https://i.ytimg.com/vi/Hq_05YpTOcY/hqdefault.jpg?sqp=-oaymwEbCMQBEG5IVfKriqkDDggBFQAAiEIYAXABwAEG&rs=AOn4CLBuilHnJRaf4MlprS1_PX2ZTJVR9g", "width": 196, "resolution": "196x110", "id": "1"}, {"height": 138, "url": "https://i.ytimg.com/vi/Hq_05YpTOcY/hqdefault.jpg?sqp=-oaymwEcCPYBEIoBSFXyq4qpAw4IARUAAIhCGAFwAcABBg==&rs=AOn4CLCF8tRByhux8DhWLBbcWgL-hcGUiA", "width": 246, "resolution": "246x138", "id": "2"}, {"height": 188, "url": "https://i.ytimg.com/vi/Hq_05YpTOcY/hqdefault.jpg?sqp=-oaymwEcCNACELwBSFXyq4qpAw4IARUAAIhCGAFwAcABBg==&rs=AOn4CLBcNPgkGn2BW89rKjp5XE-P1hr6-w", "width": 336, "resolution": "336x188", "id": "3"}], "description": "Alaska y Dinarama (1984)\r\n\r\nwww.cuandocalientaelsol.net", "upload_date": "20051207", "uploader": "Manuel M. Almeida", "uploader_id": "mmeida", "uploader_url": "http://www.youtube.com/user/mmeida", "channel_id": "UCpf25Cf_sKo_VjC5FNBrHpA", "channel_url": "https://www.youtube.com/channel/UCpf25Cf_sKo_VjC5FNBrHpA", "duration": 217, "view_count": 12818099, "average_rating": null, "age_limit": 0, "webpage_url": "https://www.youtube.com/watch?v=Hq_05YpTOcY", "categories": ["Music"], "tags": ["videoclip", "alaska", "movida", "tecno", "musica"], "is_live": null, "channel": "Manuel M. Almeida", "extractor": "youtube", "webpage_url_basename": "watch", "extractor_key": "Youtube", "playlist": null, "playlist_index": null, "thumbnail": "https://i.ytimg.com/vi/Hq_05YpTOcY/hqdefault.jpg?sqp=-oaymwEcCNACELwBSFXyq4qpAw4IARUAAIhCGAFwAcABBg==&rs=AOn4CLBcNPgkGn2BW89rKjp5XE-P1hr6-w", "display_id": "Hq_05YpTOcY", "asr": 44100, "filesize": 14232711, "format_id": "18", "format_note": "240p", "fps": 30, "height": 262, "quality": 1, "tbr": 523.778, "url": "https://rr6---sn-0opoxu-ihv6.googlevideo.com/videoplayback?expire=1670726114&ei=gu2UY_9XjpKTBv6nibAB&ip=189.173.225.87&id=o-AHpzqefD4gQpHlbjS8sloFS3JnLMJZ_M7Ez71zHRC6-4&itag=18&source=youtube&requiressl=yes&mh=im&mm=31%2C29&mn=sn-0opoxu-ihv6%2Csn-q4flrnss&ms=au%2Crdu&mv=m&mvi=6&pl=24&initcwndbps=777500&vprv=1&mime=video%2Fmp4&ns=48vzQtgGt8D6OF_Ix63ZQf4J&gir=yes&clen=14232711&ratebypass=yes&dur=217.385&lmt=1613008567714271&mt=1670704150&fvip=1&fexp=24001373%2C24007246&beids=24432615&c=WEB&txp=5438432&n=hg90v1J9EoT5OOvh4&sparams=expire%2Cei%2Cip%2Cid%2Citag%2Csource%2Crequiressl%2Cvprv%2Cmime%2Cns%2Cgir%2Cclen%2Cratebypass%2Cdur%2Clmt&lsparams=mh%2Cmm%2Cmn%2Cms%2Cmv%2Cmvi%2Cpl%2Cinitcwndbps&lsig=AG3C_xAwRQIhAIToNF6ywFSU0Nolu5row5J9MGldpb04rDslEA7gIuw9AiBWi1JJdDDn9nrXd5KKtv6aNq5lZrwKePHgBsiqtog79w%3D%3D&sig=AOq0QJ8wRAIgBbgBoeGBmTiHvzWCbMTEF8FSUGMYqOt8aiBT35TfKbACIFJoa7FXutOnwvvIe6toTi5sOvWkSGlQJt2cr5Cx74eL", "width": 352, "ext": "mp4", "vcodec": "avc1.42001E", "acodec": "mp4a.40.2", "format": "18 - 352x262 (240p)", "protocol": "https", "http_headers": {"User-Agent": "Mozilla/5.0 (Windows NT 10.0; Win64; x64) AppleWebKit/537.36 (KHTML, like Gecko) Chrome/74.0.3729.53 Safari/537.36", "Accept-Charset": "ISO-8859-1,utf-8;q=0.7,*;q=0.7", "Accept": "text/html,application/xhtml+xml,application/xml;q=0.9,*/*;q=0.8", "Accept-Encoding": "gzip, deflate", "Accept-Language": "en-us,en;q=0.5"}, "fulltitle": "Alaska y Dinarama - Ni t\u00fa ni nadie", "_filename": "Alaska y Dinarama - Ni t\u00fa ni nadie-Hq_05YpTOcY.mp4"}